README.md
datek_async_fsm/__init__.py
datek_async_fsm/errors.py
datek_async_fsm/fsm.py
datek_async_fsm/state.py
datek_async_fsm-0.2.0.dist-info/LICENSE.md
datek_async_fsm-0.2.0.dist-info/WHEEL
datek_async_fsm-0.2.0.dist-info/METADATA
datek_async_fsm-0.2.0.dist-info/RECORD
