Metadata-Version: 2.1
Name: datek-async-fsm
Version: 0.2.0
Summary: Asynchronous Finite State Machine
Home-page: https://github.com/DAtek/datek-async-fsm/
License: MIT
Author: Attila Dudas
Requires-Python: >=3.9,<4.0
Classifier: License :: OSI Approved :: MIT License
Classifier: Programming Language :: Python :: 3
Classifier: Programming Language :: Python :: 3.10
Classifier: Programming Language :: Python :: 3.9
Project-URL: Repository, https://github.com/DAtek/datek-async-fsm/
